docfilter/__init__.py
docfilter/dict_filter.py
docfilter/ml_filter.py
docfilter/profanity_check.py
docfilter/re_filter.py
docfilter/sanity_check.py
docfilter-0.1.0.dist-info/METADATA
docfilter-0.1.0.dist-info/WHEEL
docfilter-0.1.0.dist-info/top_level.txt
docfilter-0.1.0.dist-info/RECORD
