Metadata-Version: 2.1
Name: docfilter
Version: 0.1.0
Summary: The Python package docfilter is used to detect and remove inappropriate information from text.
Home-page: https://github.com/DSDanielPark/docfilter
Author: parkminwoo
Author-email: parkminwoo1991@gmail.com
Requires-Python: >=3.6
Requires-Dist: re
Requires-Dist: pandas
